<?xml version="1.0" encoding="utf-8"?>
<eml:eml xmlns:eml="eml://ecoinformatics.org/eml-2.1.1" xmlns:xsi="http://www.w3.org/2001/XMLSchema-instance" xsi:schemaLocation="eml://ecoinformatics.org/eml-2.1.1 http://rs.gbif.org/schema/eml-gbif-profile/1.1/eml.xsd"
        packageId="col-clb-1044"  system="http://catalogueoflife.org" scope="system"
  xml:lang="en">


<dataset>
  <title>World Porifera Database</title>
  <shortName>WoRMS Porifera</shortName>
  <associatedParty>
    <individualName>
      <givenName>Belinda</givenName>
      <surName>Alvarez</surName>
    </individualName>
    <electronicMailAddress>Belinda.glasby@gmail.com</electronicMailAddress>
    <role>editor</role>
  </associatedParty>
  <associatedParty>
    <individualName>
      <givenName>Nicole</givenName>
      <surName>Boury-Esnault</surName>
    </individualName>
    <electronicMailAddress>info@marinespecies.org</electronicMailAddress>
    <role>editor</role>
  </associatedParty>
  <associatedParty>
    <individualName>
      <givenName>José Luis</givenName>
      <surName>Carballo</surName>
    </individualName>
    <electronicMailAddress>jlcarballo@ola.icmyl.unam.mx</electronicMailAddress>
    <role>editor</role>
  </associatedParty>
  <associatedParty>
    <individualName>
      <givenName>Paco</givenName>
      <surName>Cárdenas</surName>
    </individualName>
    <electronicMailAddress>paco.cardenas@fkog.uu.se</electronicMailAddress>
    <role>editor</role>
  </associatedParty>
  <associatedParty>
    <individualName>
      <givenName>Nicole</givenName>
      <surName>de Voogd</surName>
      <userId>https://orcid.org/0000-0002-7985-5604</userId>
    </individualName>
    <electronicMailAddress>nicole.devoogd@naturalis.nl</electronicMailAddress>
    <role>editor</role>
  </associatedParty>
  <associatedParty>
    <individualName>
      <givenName>Maria-Cristina</givenName>
      <surName>Díaz</surName>
    </individualName>
    <electronicMailAddress>taxochica@gmail.com</electronicMailAddress>
    <role>editor</role>
  </associatedParty>
  <associatedParty>
    <individualName>
      <givenName>Martin</givenName>
      <surName>Dohrmann</surName>
    </individualName>
    <electronicMailAddress>m.dohrmann@lrz.uni-muenchen.de</electronicMailAddress>
    <role>editor</role>
  </associatedParty>
  <associatedParty>
    <individualName>
      <givenName>Rachel</givenName>
      <surName>Downey</surName>
    </individualName>
    <electronicMailAddress>Rachel.downey@anu.edu.au</electronicMailAddress>
    <role>editor</role>
  </associatedParty>
  <associatedParty>
    <individualName>
      <givenName>Eduardo</givenName>
      <surName>Hajdu</surName>
    </individualName>
    <electronicMailAddress>eduardo.hajdu@gmail.com</electronicMailAddress>
    <role>editor</role>
  </associatedParty>
  <associatedParty>
    <individualName>
      <givenName>John</givenName>
      <surName>Hooper</surName>
      <userId>https://orcid.org/0000-0003-1722-5954</userId>
    </individualName>
    <electronicMailAddress>john.hooper@qm.qld.gov.au</electronicMailAddress>
    <role>editor</role>
  </associatedParty>
  <associatedParty>
    <individualName>
      <givenName>Michelle</givenName>
      <surName>Kelly</surName>
    </individualName>
    <electronicMailAddress>Michelle.Kelly@niwa.co.nz</electronicMailAddress>
    <role>editor</role>
  </associatedParty>
  <associatedParty>
    <individualName>
      <givenName>Michelle</givenName>
      <surName>Klautau</surName>
    </individualName>
    <electronicMailAddress>mklautau@biologia.ufrj.br</electronicMailAddress>
    <role>editor</role>
  </associatedParty>
  <associatedParty>
    <individualName>
      <givenName>Renata</givenName>
      <surName>Manconi</surName>
      <userId>https://orcid.org/0000-0002-7619-8493</userId>
    </individualName>
    <electronicMailAddress>rmanconi@uniss.it</electronicMailAddress>
    <role>editor</role>
  </associatedParty>
  <associatedParty>
    <individualName>
      <givenName>Christine</givenName>
      <surName>Morrow</surName>
    </individualName>
    <electronicMailAddress>christinemorrow@gmail.com</electronicMailAddress>
    <role>editor</role>
  </associatedParty>
  <associatedParty>
    <individualName>
      <givenName>Andrzej</givenName>
      <surName>Pisera</surName>
    </individualName>
    <electronicMailAddress>apis@twarda.pan.pl</electronicMailAddress>
    <role>editor</role>
  </associatedParty>
  <associatedParty>
    <individualName>
      <givenName>Pilar</givenName>
      <surName>Ríos</surName>
    </individualName>
    <electronicMailAddress>pilar.rios.lopez@gmail.com</electronicMailAddress>
    <role>editor</role>
  </associatedParty>
  <associatedParty>
    <individualName>
      <givenName>Klaus</givenName>
      <surName>Rützler</surName>
    </individualName>
    <electronicMailAddress>RUETZLER@si.edu</electronicMailAddress>
    <role>editor</role>
  </associatedParty>
  <associatedParty>
    <individualName>
      <givenName>Christine</givenName>
      <surName>Schönberg</surName>
      <userId>https://orcid.org/0000-0001-6286-8196</userId>
    </individualName>
    <electronicMailAddress>cschoenberg@mail.nsysu.edu.tw</electronicMailAddress>
    <role>editor</role>
  </associatedParty>
  <associatedParty>
    <individualName>
      <givenName>Jean</givenName>
      <surName>Vacelet</surName>
    </individualName>
    <electronicMailAddress>info@marinespecies.org</electronicMailAddress>
    <role>editor</role>
  </associatedParty>
  <associatedParty>
    <individualName>
      <givenName>Rob</givenName>
      <surName>van Soest</surName>
    </individualName>
    <electronicMailAddress>Rob.vanSoest@naturalis.nl</electronicMailAddress>
    <role>editor</role>
  </associatedParty>
  <associatedParty>
    <address>
      <country>Australia</country>
    </address>
    <role>contributor</role>
  </associatedParty>
  <associatedParty>
    <role>contributor</role>
  </associatedParty>
  <associatedParty>
    <role>contributor</role>
  </associatedParty>
  <associatedParty>
    <address>
      <country>Sweden</country>
    </address>
    <role>contributor</role>
  </associatedParty>
  <associatedParty>
    <address>
      <country>Netherlands</country>
    </address>
    <role>contributor</role>
  </associatedParty>
  <associatedParty>
    <address>
      <country>Venezuela</country>
    </address>
    <role>contributor</role>
  </associatedParty>
  <associatedParty>
    <address>
      <country>Germany</country>
    </address>
    <role>contributor</role>
  </associatedParty>
  <associatedParty>
    <address>
      <country>Australia</country>
    </address>
    <role>contributor</role>
  </associatedParty>
  <associatedParty>
    <address>
      <country>Brazil</country>
    </address>
    <role>contributor</role>
  </associatedParty>
  <associatedParty>
    <address>
      <country>Australia</country>
    </address>
    <role>contributor</role>
  </associatedParty>
  <associatedParty>
    <address>
      <country>Australia</country>
    </address>
    <role>contributor</role>
  </associatedParty>
  <associatedParty>
    <address>
      <country>Brazil</country>
    </address>
    <role>contributor</role>
  </associatedParty>
  <associatedParty>
    <address>
      <country>Italy</country>
    </address>
    <role>contributor</role>
  </associatedParty>
  <associatedParty>
    <address>
      <country>UnitedKingdom</country>
    </address>
    <role>contributor</role>
  </associatedParty>
  <associatedParty>
    <address>
      <country>Poland</country>
    </address>
    <role>contributor</role>
  </associatedParty>
  <associatedParty>
    <address>
      <country>Spain</country>
    </address>
    <role>contributor</role>
  </associatedParty>
  <associatedParty>
    <address>
      <country>UnitedStates</country>
    </address>
    <role>contributor</role>
  </associatedParty>
  <associatedParty>
    <address>
      <country>UnitedStates</country>
    </address>
    <role>contributor</role>
  </associatedParty>
  <associatedParty>
    <address>
      <country>Belgium</country>
    </address>
    <role>contributor</role>
  </associatedParty>
    <pubDate>2022-07-01</pubDate>
  <language>english</language>
  <abstract>
    <para>The World Porifera database is a searchable catalogue of recent sponge species and higher taxon names. The catalogue is intended to promote stability and act as a tool for higher taxon revisions, regional monographs, and eventually as a catalogue of the world’s sponge specimen databases as these are slowly being accumulated through EurOBIS and GBIF. Data are contributed to the Catalogue of Life via the World Register of Marine Species (WoRMS), hosted by the Flanders Marine Institute (VLIZ).</para>
  </abstract>
  <intellectualRights>
    <para><ulink url="http://creativecommons.org/licenses/by/4.0/legalcode"><citetitle>Creative Commons Attribution (CC BY) 4.0</citetitle></ulink></para>
  </intellectualRights>
  <distribution scope="document">
    <online>
      <url function="information">https://www.marinespecies.org/porifera</url>
    </online>
  </distribution>
  <coverage>
    <geographicCoverage>
      <geographicDescription>Global</geographicDescription>
    </geographicCoverage>
    <taxonomicCoverage>
      <generalTaxonomicCoverage>sponges</generalTaxonomicCoverage>
    </taxonomicCoverage>
    </coverage>
  <contact>
    <individualName>
      <givenName>Nicole</givenName>
      <surName>de Voogd</surName>
    </individualName>
    <electronicMailAddress>nicole.devoogd@naturalis.nl</electronicMailAddress>
  </contact>
</dataset>

<additionalMetadata>
  <metadata>
    <gbif>
      <citation>Alvarez, B., Boury-Esnault, N., Carballo, J. L., Cárdenas, P., de Voogd, N., Díaz, M.-C., Dohrmann, M., Downey, R., Hajdu, E., Hooper, J., Kelly, M., Klautau, M., Manconi, R., Morrow, C., Pisera, A., Ríos, P., Rützler, K., Schönberg, C., Vacelet, J., &amp; van Soest, R. (2022). World Porifera Database. In O. Bánki, Y. Roskov, M. Döring, G. Ower, L. Vandepitte, D. Hobern, D. Remsen, P. Schalk, R. E. DeWalt, M. Keping, J. Miller, T. Orrell, R. Aalbu, R. Adlard, E. M. Adriaenssens, C. Aedo, E. Aescht, N. Akkari, P. Alfenas-Zerbini, et al., Catalogue of Life Checklist (ver. (07/2022)). https://doi.org/10.48580/dfpz-392</citation>
      <resourceLogoUrl>https://www.marinespecies.org/documents/WoRMS%20branding/WoRMS_logo_blue_negative.png</resourceLogoUrl>
    </gbif>
    <col>
      <version>ver. (07/2022)</version>
      <completeness>96</completeness>
      <confidence>5</confidence>
    </col>
  </metadata>
</additionalMetadata>

</eml:eml>
